{
    "type": "FeatureCollection",
    "crs": {
        "type": "name",
        "properties": {
            "name": "urn:ogc:def:crs:OGC:1.3:CRS84"
        }
    },
    "features": [
        {
            "type": "Feature",
            "properties": {
                "sna": "A商圈",
				"sno": 500201001,
                "type": "nightmarket",
				"city": "台北市",
				"district": "中正區"
            },
            "geometry": {
                "type": "Point",
                "coordinates": [
                    121.5436,
                    25.02605
                ]
            }
        }
    ]
}

